duckdb_extension/__init__.py
duckdb_extension/duckdb_extension.py
duckdb_extension/example_usage.py
duckdb_spark-1.0.4.dist-info/LICENSE
duckdb_spark-1.0.4.dist-info/METADATA
duckdb_spark-1.0.4.dist-info/WHEEL
duckdb_spark-1.0.4.dist-info/top_level.txt
duckdb_spark-1.0.4.dist-info/RECORD
