Metadata-Version: 2.1
Name: duckdb-spark
Version: 1.0.4
Summary: A custom PySpark extension for writing data to DuckDB
Home-page: https://github.com/ChannabasavAngadi/spark_duckDB_extension.git
Author: Channabasav Angadi
Author-email: channuangadi077@gmail.com
License: UNKNOWN
Platform: UNKNOWN
Classifier: Programming Language :: Python :: 3
Classifier: License :: OSI Approved :: MIT License
Classifier: Operating System :: OS Independent
Requires-Python: >=3.6
License-File: LICENSE
Requires-Dist: duckdb (>=0.3.0)
Requires-Dist: pyspark (>=3.0.0)
